torch2jax/__init__.py
torch2jax-0.1.0.dist-info/METADATA
torch2jax-0.1.0.dist-info/WHEEL
torch2jax-0.1.0.dist-info/top_level.txt
torch2jax-0.1.0.dist-info/RECORD
