Metadata-Version: 2.2
Name: torch2jax
Version: 0.1.0
Summary: Run PyTorch in JAX. 🤝
Author-email: Samuel Ainsworth <skainsworth@gmail.com>
Project-URL: Homepage, https://github.com/samuela/torch2jax
Project-URL: Bug Tracker, https://github.com/samuela/torch2jax/issues
Requires-Dist: jax
Requires-Dist: torch
